README.md
setup.py
cleandev_config_loader.egg-info/PKG-INFO
cleandev_config_loader.egg-info/SOURCES.txt
cleandev_config_loader.egg-info/dependency_links.txt
cleandev_config_loader.egg-info/requires.txt
cleandev_config_loader.egg-info/top_level.txt
properties_loader/__init__.py
properties_loader/exceptions.py
properties_loader/inmutables.py
properties_loader/interfaces.py