Metadata-Version: 2.1
Name: cleandev-config-loader
Version: 0.3.1
Summary: Loader for properties.ini make more easy
Home-page: https://gitlab.com/cleansoftware/libs/public/config-loader
Author: Daniel Rodriguez Rodriguez
Author-email: danielrodriguezrodriguez.pks@gmail.com
License: UNKNOWN
Project-URL: Bug Tracker, https://gitlab.com/cleansoftware/libs/public/config-loader/-/issues
Platform: UNKNOWN
Classifier: Programming Language :: Python :: 3
Classifier: License :: OSI Approved :: MIT License
Classifier: Operating System :: OS Independent
Requires-Python: >=3.9
